README.md
setup.cfg
setup.py
distributions/Binomialdistribution.py
distributions/Gaussiandistribution.py
distributions/Generaldistribution.py
distributions/__init__.py
p1ckett_distributions.egg-info/PKG-INFO
p1ckett_distributions.egg-info/SOURCES.txt
p1ckett_distributions.egg-info/dependency_links.txt
p1ckett_distributions.egg-info/not-zip-safe
p1ckett_distributions.egg-info/top_level.txt